CHANGELOG.txt
LICENCE.txt
MANIFEST.in
README.txt
setup.py
mul_div/__init__.py
shubham_MUL_DIV2.egg-info/PKG-INFO
shubham_MUL_DIV2.egg-info/SOURCES.txt
shubham_MUL_DIV2.egg-info/dependency_links.txt
shubham_MUL_DIV2.egg-info/top_level.txt